{
  "pages": {
    "noOfPages": 1,
    "medianOnLoad": null,
    "ninetyFifthOnLoad": null,
    "pages": [
      {
        "url": "CarMax",
        "onLoad": null
      }
    ]
  },
  "requests": {
    "all": {
      "noOfRequests": 121,
      "medianTime": 70,
      "ninetyFifthTime": 356,
      "medianTimings": {
        "blocked": -1,
        "wait": 35,
        "receive": 0
      },
      "ninetyFifthTimings": {
        "blocked": 0,
        "wait": 118,
        "receive": 48
      },
      "bytesTransferred": null,
      "topUrl": {
        "url": "https://www.googletagmanager.com/gtag/js",
        "noOfOccurrences": 9
      },
      "largest": {
        "url": "https://pt.ispot.tv/v2/TC-3665-1.gif",
        "bytes": 0
      },
      "largestCompressed": {
        "url": "https://www.carmax.com/"
      },
      "longest": {
        "url": "https://www.carmax.com/",
        "time": 519,
        "timings": {
          "blocked": 0,
          "wait": 202,
          "receive": 11,
          "connect": 264
        }
      }
    },
    "document": {
      "noOfRequests": 0
    },
    "font": {
      "noOfRequests": 0
    },
    "image": {
      "noOfRequests": 0
    },
    "style": {
      "noOfRequests": 0
    },
    "script": {
      "noOfRequests": 0
    },
    "xhr": {
      "noOfRequests": 0
    },
    "other": {
      "noOfRequests": 0
    }
  }
}