{
  "pages": {
    "noOfPages": 1,
    "medianOnLoad": null,
    "ninetyFifthOnLoad": null,
    "pages": [
      {
        "url": "Allstate",
        "onLoad": null
      }
    ]
  },
  "requests": {
    "all": {
      "noOfRequests": 72,
      "medianTime": 91,
      "ninetyFifthTime": 460,
      "medianTimings": {
        "blocked": -1,
        "wait": 36,
        "receive": 0
      },
      "ninetyFifthTimings": {
        "blocked": 0,
        "wait": 169,
        "receive": 84
      },
      "bytesTransferred": null,
      "topUrl": {
        "url": "https://www.allstate.com/WNwJWx/Hk/w2/ODcF/L5CsquHGOY/aiQYVX2k/E0B3bzkhJAE/GBM/uZXk-VjcB",
        "noOfOccurrences": 3
      },
      "largest": {
        "url": "https://data.allstate.com/529001/fragile.html",
        "bytes": 0
      },
      "largestCompressed": {
        "url": "https://www.allstate.com/"
      },
      "longest": {
        "url": "https://lpcdn.lpsnmedia.net/le_unified_window/10.23.0.0-release_5549/desktopEmbedded.js",
        "time": 1034,
        "timings": {
          "blocked": 0,
          "wait": 91,
          "receive": 576,
          "connect": 366
        }
      }
    },
    "document": {
      "noOfRequests": 0
    },
    "font": {
      "noOfRequests": 0
    },
    "image": {
      "noOfRequests": 0
    },
    "style": {
      "noOfRequests": 0
    },
    "script": {
      "noOfRequests": 0
    },
    "xhr": {
      "noOfRequests": 0
    },
    "other": {
      "noOfRequests": 0
    }
  }
}