{
  "pages": {
    "noOfPages": 1,
    "medianOnLoad": null,
    "ninetyFifthOnLoad": null,
    "pages": [
      {
        "url": "Honeywell International",
        "onLoad": null
      }
    ]
  },
  "requests": {
    "all": {
      "noOfRequests": 148,
      "medianTime": 38,
      "ninetyFifthTime": 349,
      "medianTimings": {
        "blocked": -1,
        "wait": 34,
        "receive": 0
      },
      "ninetyFifthTimings": {
        "blocked": 0,
        "wait": 70,
        "receive": 24
      },
      "bytesTransferred": null,
      "topUrl": {
        "url": "https://www.honeywell.com/libs/dam/components/scene7/common/clientlibs/i18n.js",
        "noOfOccurrences": 1
      },
      "largest": {
        "url": "https://edge.microsoft.com/autofillservice/v1/pages/ChVDaHJvbWUvMTA3LjAuNTMwNC4xNTASHgnTWuWQIN8J_xIFDcd58iASBQ3HefIgEgUNpZM2JA==",
        "bytes": 0
      },
      "largestCompressed": {
        "url": "https://arrow-digital.my.salesforce-sites.com/einsteinbot/resource/ArrowBotFiles/js/SnapInChat.js"
      },
      "longest": {
        "url": "https://edge.microsoft.com/autofillservice/v1/pages/ChVDaHJvbWUvMTA3LjAuNTMwNC4xNTASHgnTWuWQIN8J_xIFDcd58iASBQ3HefIgEgUNpZM2JA==",
        "time": 1196,
        "timings": {
          "blocked": 0,
          "wait": 1055,
          "receive": 0,
          "connect": 140
        }
      }
    },
    "document": {
      "noOfRequests": 0
    },
    "font": {
      "noOfRequests": 0
    },
    "image": {
      "noOfRequests": 0
    },
    "style": {
      "noOfRequests": 0
    },
    "script": {
      "noOfRequests": 0
    },
    "xhr": {
      "noOfRequests": 0
    },
    "other": {
      "noOfRequests": 0
    }
  }
}