{
  "pages": {
    "noOfPages": 1,
    "medianOnLoad": null,
    "ninetyFifthOnLoad": null,
    "pages": [
      {
        "url": "Tyson Foods",
        "onLoad": null
      }
    ]
  },
  "requests": {
    "all": {
      "noOfRequests": 61,
      "medianTime": 61,
      "ninetyFifthTime": 306,
      "medianTimings": {
        "blocked": -1,
        "wait": 43,
        "receive": 1
      },
      "ninetyFifthTimings": {
        "blocked": 0,
        "wait": 71,
        "receive": 51
      },
      "bytesTransferred": null,
      "topUrl": {
        "url": "https://nav-edge.smartscreen.microsoft.com/api/browser/edge/navigate/3",
        "noOfOccurrences": 2
      },
      "largest": {
        "url": "https://www.tysonfoods.com/themes/custom/tyson/favicons/favicon.ico",
        "bytes": 0
      },
      "largestCompressed": {
        "url": "https://nav-edge.smartscreen.microsoft.com/api/browser/edge/navigate/3"
      },
      "longest": {
        "url": "https://cloud.typography.com/7091356/7473192/css/fonts.css",
        "time": 528,
        "timings": {
          "blocked": 0,
          "wait": 212,
          "receive": 0,
          "connect": 274
        }
      }
    },
    "document": {
      "noOfRequests": 0
    },
    "font": {
      "noOfRequests": 0
    },
    "image": {
      "noOfRequests": 0
    },
    "style": {
      "noOfRequests": 0
    },
    "script": {
      "noOfRequests": 0
    },
    "xhr": {
      "noOfRequests": 0
    },
    "other": {
      "noOfRequests": 0
    }
  }
}