{
  "pages": {
    "noOfPages": 1,
    "medianOnLoad": null,
    "ninetyFifthOnLoad": null,
    "pages": [
      {
        "url": "Performance Food Group",
        "onLoad": null
      }
    ]
  },
  "requests": {
    "all": {
      "noOfRequests": 63,
      "medianTime": 58,
      "ninetyFifthTime": 292,
      "medianTimings": {
        "blocked": -1,
        "wait": 32,
        "receive": 0
      },
      "ninetyFifthTimings": {
        "blocked": 0,
        "wait": 81,
        "receive": 70
      },
      "bytesTransferred": null,
      "topUrl": {
        "url": "https://a.dpmsrv.com/dpmpxl/index.php",
        "noOfOccurrences": 1
      },
      "largest": {
        "url": "https://www.pfgc.com/favicon.ico",
        "bytes": 0
      },
      "largestCompressed": {
        "url": "https://nav-edge.smartscreen.microsoft.com/api/browser/edge/navigate/3"
      },
      "longest": {
        "url": "https://use.typekit.net/blx0lvw.js",
        "time": 433,
        "timings": {
          "blocked": 0,
          "wait": 28,
          "receive": 0,
          "connect": 366
        }
      }
    },
    "document": {
      "noOfRequests": 0
    },
    "font": {
      "noOfRequests": 0
    },
    "image": {
      "noOfRequests": 0
    },
    "style": {
      "noOfRequests": 0
    },
    "script": {
      "noOfRequests": 0
    },
    "xhr": {
      "noOfRequests": 0
    },
    "other": {
      "noOfRequests": 0
    }
  }
}